finndex/__init__.py
finndex/aggregate/historical.py
finndex/aggregate/instantaneous.py
finndex/aggregate/sliders.py
finndex/api/datadict.py
finndex/fundamental/coinmetrics.py
finndex/graphing/gauge.py
finndex/graphing/timeseries.py
finndex/sentiment/fearandgreed.py
finndex/sentiment/nlp.py
finndex/sentiment/trends.py
finndex/util/cryptocurrencies.py
finndex/util/dateutil.py
finndex/util/mathutil.py
finndex/util/webutil.py
finndex-0.2.1.dist-info/LICENSE
finndex-0.2.1.dist-info/METADATA
finndex-0.2.1.dist-info/WHEEL
finndex-0.2.1.dist-info/top_level.txt
finndex-0.2.1.dist-info/RECORD
